MANIFEST.in
README.md
requirements.txt
setup.py
red_cipher/__init__.py
red_cipher/__main__.py
red_cipher/actions.py
red_cipher/aes_encryptor.py
red_cipher/banner.py
red_cipher/handle_json.py
red_cipher/rsa_encryptor.py
redcipher.egg-info/PKG-INFO
redcipher.egg-info/SOURCES.txt
redcipher.egg-info/dependency_links.txt
redcipher.egg-info/entry_points.txt
redcipher.egg-info/requires.txt
redcipher.egg-info/top_level.txt