Metadata-Version: 2.1
Name: redcipher
Version: 1.5
Summary: Professional Encryption / Decryption program !
Home-page: https://github.com/RedMads/RedCipher/
Author: RedMads
Author-email: redmads@protonmail.com
License: MIT
Project-URL: Source, https://github.com/RedMads/RedCipher
Project-URL: Report Bugs, https://github.com/RedMads/RedCipher/issues
Project-URL: Download, https://pypi.org/project/redcipher/#files
Project-URL: Documentation, https://github.com/RedMads/RedCipher/blob/master/README.md
Keywords: python,encrypt,decrypt,cipher,cryptography,crypto,AES,RSA,decryption,encryption
Platform: UNKNOWN
